<?xml version="1.0" encoding="utf-16"?>
<post>
  <id>приключения-тома-сойера</id>
  <title>Приключения Тома Сойера</title>
  <slug>приключения-тома-сойера</slug>
  <correlationkey />
  <author>Admin</author>
  <pubDate>2018-08-27T06:20:48.2373228Z</pubDate>
  <lastModified>2018-08-27T06:20:48</lastModified>
  <excerpt />
  <content>        &lt;div class="float-md-left simple-side-image mr-md-2"&gt;
            &lt;img class="image-responsive" src="/nk/&amp;#x43F;&amp;#x440;&amp;#x438;&amp;#x43A;&amp;#x43B;&amp;#x44E;&amp;#x447;&amp;#x435;&amp;#x43D;&amp;#x438;&amp;#x44F;-&amp;#x442;&amp;#x43E;&amp;#x43C;&amp;#x430;-&amp;#x441;&amp;#x43E;&amp;#x439;&amp;#x435;&amp;#x440;&amp;#x430;1-200x300.jpg" /&gt;
        &lt;/div&gt;
&lt;p&gt;Автор: Марк Твен&lt;/p&gt;

&lt;p&gt;Год выпуска: 1980&lt;/p&gt;

&lt;p&gt;Издательство:&lt;/p&gt;

&lt;p&gt;Переплет:&lt;/p&gt;

&lt;p&gt;Страниц:&lt;/p&gt;


</content>
  <contentType>html</contentType>
  <imageUrl />
  <thumbnailUrl />
  <createdUtc>2018-08-27T06:18:58</createdUtc>
  <createdByUser>admin</createdByUser>
  <lastModifiedByUser>admin</lastModifiedByUser>
  <draftAuthor />
  <draftContent />
  <draftPubDate />
  <templateKey>sct-ImageWithContent</templateKey>
  <serializedModel>{"Content":"&lt;p&gt;Автор: Марк Твен&lt;/p&gt;\r\n\r\n&lt;p&gt;Год выпуска: 1980&lt;/p&gt;\r\n\r\n&lt;p&gt;Издательство:&lt;/p&gt;\r\n\r\n&lt;p&gt;Переплет:&lt;/p&gt;\r\n\r\n&lt;p&gt;Страниц:&lt;/p&gt;\r\n","ResizedUrl":"/nk/приключения-тома-сойера1-200x300.jpg","FullSizeUrl":"/nk/приключения-тома-сойера1-200x300.jpg","AltText":null,"Layout":"ImageOnLeft"}</serializedModel>
  <draftSerializedModel />
  <serializer>Json</serializer>
  <blogId>831351e2-9788-4c59-91e1-03dfec6205cf</blogId>
  <ispublished>true</ispublished>
  <isFeatured>false</isFeatured>
  <autoTeaser></autoTeaser>
  <teaserOverride />
  <suppressTeaser>false</suppressTeaser>
  <categories></categories>
  <comments></comments>
</post>