{"RequireCookieConsent":true,"CookiePolicySummary":"Для удобства Вашей работы сайт использует файлы cookies.","ConcurrencyStamp":"d4aba576-70ef-4ab3-aeb9-e762251d2204","Theme":"custom1","AllowNewRegistration":true,"RequireConfirmedEmail":false,"RequireConfirmedPhone":false,"UseLdapAuth":false,"AllowDbFallbackWithLdap":false,"EmailLdapDbFallback":false,"AutoCreateLdapUserOnFirstLogin":true,"LdapServer":"","LdapDomain":null,"LdapPort":389,"LdapRootDN":"","LdapUserDNKey":"CN","UseEmailForLogin":true,"DisableDbAuth":false,"RequiresQuestionAndAnswer":false,"RequireApprovalBeforeLogin":false,"AccountApprovalEmailCsv":null,"MaxInvalidPasswordAttempts":10,"MinRequiredPasswordLength":7,"PwdRequireNonAlpha":true,"PwdRequireLowercase":true,"PwdRequireUppercase":true,"PwdRequireDigit":true,"AllowPersistentLogin":true,"CaptchaOnRegistration":false,"CaptchaOnLogin":false,"RecaptchaPrivateKey":null,"RecaptchaPublicKey":null,"UseInvisibleRecaptcha":false,"FacebookAppId":null,"FacebookAppSecret":null,"MicrosoftClientId":null,"MicrosoftClientSecret":null,"GoogleClientId":null,"GoogleClientSecret":null,"TwitterConsumerKey":null,"TwitterConsumerSecret":null,"OidConnectAppId":null,"OidConnectAppSecret":null,"OidConnectAuthority":null,"OidConnectDisplayName":null,"AddThisDotComUsername":null,"TimeZoneId":"Asia/Omsk","CompanyName":null,"CompanyStreetAddress":null,"CompanyStreetAddress2":null,"CompanyLocality":null,"CompanyRegion":null,"CompanyPostalCode":null,"CompanyCountry":null,"CompanyPhone":null,"CompanyFax":null,"CompanyPublicEmail":null,"CompanyWebsite":null,"DefaultEmailFromAddress":null,"DefaultEmailFromAlias":null,"SmtpUser":null,"SmtpPassword":null,"SmtpPort":25,"SmtpPreferredEncoding":null,"SmtpServer":null,"SmtpRequiresAuth":false,"SmtpUseSsl":false,"DkimPublicKey":null,"DkimPrivateKey":null,"DkimDomain":null,"DkimSelector":null,"SignEmailWithDkim":false,"EmailSenderName":"SmtpMailSender","EmailApiKey":null,"EmailApiEndpoint":null,"SmsClientId":null,"SmsSecureToken":null,"SmsFrom":null,"GoogleAnalyticsProfileId":null,"RegistrationAgreement":null,"RegistrationPreamble":null,"LoginInfoTop":null,"LoginInfoBottom":null,"SiteIsClosed":false,"SiteIsClosedMessage":null,"PrivacyPolicy":null,"IsDataProtected":false,"TermsUpdatedUtc":"2018-08-24T19:24:32.7925814Z","ForcedCulture":null,"ForcedUICulture":null,"Id":"5a43fdc2-c1f3-485a-b59c-54b5c2bbdd46","AliasId":"s1","SiteName":"BookTracking - доступная система библиотечного учета","SiteFolderName":null,"PreferredHostName":null,"IsServerAdminSite":true,"CreatedUtc":"2018-08-24T19:24:32.7928436Z","LastModifiedUtc":"2018-08-24T20:49:55.5068957Z"}