<?xml version="1.0" encoding="utf-16"?>
<post>
  <id>как-бабы-яги-сказку-спасали</id>
  <title>Как бабы яги сказку спасали</title>
  <slug>как-бабы-яги-сказку-спасали</slug>
  <correlationkey />
  <author>Admin</author>
  <pubDate>2018-08-27T06:51:40.8241457Z</pubDate>
  <lastModified>2018-08-27T06:51:40</lastModified>
  <excerpt />
  <content>        &lt;div class="float-md-left simple-side-image mr-md-2"&gt;
            &lt;img class="image-responsive" src="/nk/rezizlsiiac.jpg" /&gt;
        &lt;/div&gt;
&lt;p&gt;Автор: Михаил Мокенко&lt;/p&gt;

&lt;p&gt;Год выпуска: -&lt;/p&gt;

&lt;p&gt;Издательство:&lt;/p&gt;

&lt;p&gt;Переплет:&lt;/p&gt;

&lt;p&gt;Страниц:&lt;/p&gt;


</content>
  <contentType>html</contentType>
  <imageUrl />
  <thumbnailUrl />
  <createdUtc>2018-08-27T06:50:26</createdUtc>
  <createdByUser>admin</createdByUser>
  <lastModifiedByUser>admin</lastModifiedByUser>
  <draftAuthor />
  <draftContent />
  <draftPubDate />
  <templateKey>sct-ImageWithContent</templateKey>
  <serializedModel>{"Content":"&lt;p&gt;Автор: Михаил Мокенко&lt;/p&gt;\r\n\r\n&lt;p&gt;Год выпуска: -&lt;/p&gt;\r\n\r\n&lt;p&gt;Издательство:&lt;/p&gt;\r\n\r\n&lt;p&gt;Переплет:&lt;/p&gt;\r\n\r\n&lt;p&gt;Страниц:&lt;/p&gt;\r\n","ResizedUrl":"/nk/rezizlsiiac.jpg","FullSizeUrl":"/nk/rezizlsiiac.jpg","AltText":null,"Layout":"ImageOnLeft"}</serializedModel>
  <draftSerializedModel />
  <serializer>Json</serializer>
  <blogId>831351e2-9788-4c59-91e1-03dfec6205cf</blogId>
  <ispublished>true</ispublished>
  <isFeatured>false</isFeatured>
  <autoTeaser></autoTeaser>
  <teaserOverride />
  <suppressTeaser>false</suppressTeaser>
  <categories></categories>
  <comments></comments>
</post>